Workbook

Sheet Chronogramme
B2: Etat | C2: N° | D2: Type de stimuli | E2: Personnage | F2: Destinataire | G2: Objet | H2: Corps | I2: Modalité
B3: Tango 1 - biomed attaqué CHU et CHOR + problèmes réseau CHU
B4: ✅ | C4: T1-1 | D4: Structurant | E4: Chef de service cardiologie | F4: CCD CHU | G4: ="Panne "&Applicatifs!$B$6&" (Laboratoire)" -> Panne INLOG (Laboratoire) | H4: ="Bonjour, il semblerait qu'il y ait une panne au niveau du laboratoire de biologie. "&Applicatifs!$B$6&" est en panne. On doit se déplacer pour avoir les résultats, c'est très long et on a beaucoup de mal à tenir le rythme." -> Bonjour, il semblerait qu'il y ait une panne au niveau du laboratoire de biologie. INLOG est en panne. On doit se déplacer pour avoir les résultats, c'est très long et on a beaucoup de mal à tenir le rythme. | I4: Appel
B5: ✅ | C5: T1-2 | D5: Structurant | E5: Responsable imagerie | F5: CCD CHU | G5: Ralentissement PACS | H5: Bonjour, je vous appelle parce qu'il semblerait qu'il y ait un ralentissement du PACS. On a de plus en plus de mal à pouvoir consulter les résultats d'imagerie, c'est vraiment contraignant. A ce rythme là, on devra bientôt se déplacer pour les consulter directement sur les appareils d'imagerie. On perd un temps fou ! | I5: Appel
B6: ✅ | C6: T1-3 | D6: Structurant | E6: Infirmière | F6: CCD CHOR | G6: Panne Laboratoire | H6: ="Bonjour, il semblerait qu'il y ait une panne au niveau du laboratoire de biologie. On doit se déplacer pour avoir les résultats, c'est très long et on a beaucoup de mal à tenir le rythme." -> Bonjour, il semblerait qu'il y ait une panne au niveau du laboratoire de biologie. On doit se déplacer pour avoir les résultats, c'est très long et on a beaucoup de mal à tenir le rythme. | I6: Appel
B7: ✅ | C7: T1-4 | D7: Structurant | E7: Accueil | F7: CCD CHU | G7: Pop up Windows suspectes | H7: Bonjour, on arrête pas d'avoir des fenêtres qui s'ouvrent sans arrêt sur les postes avec des messages en anglais étranges. On dirait que l'ordinateur est hanté !! | I7: Appel
B8: ✅ | C8: T1-5 | D8: Structurant | E8: Cadre de santé | F8: CCD CHU | G8: Pop up Windows suspectes | H8: Bonjour, on arrête pas d'avoir des fenêtres qui s'ouvrent sans arrêt sur les postes avec des messages en anglais étranges. On dirait que l'ordinateur est hanté !! | I8: Appel
B9: ✅ | C9: T1-6 | D9: Structurant | E9: Responsable RH | F9: CCD CHU | G9: Pop up Windows suspectes | H9: Bonjour, on arrête pas d'avoir des fenêtres qui s'ouvrent sans arrêt sur les postes avec des messages en anglais étranges. On dirait que l'ordinateur est hanté !! | I9: Appel
B10: ✅ | C10: T1-7 | D10: Structurant | E10: Technicien informatique | F10: CCD CHU | G10: Pop up Windows suspectes | H10: Bonjour, j'ai constaté que des messages de service Windows suspects s'affichent sur les écrans de nombreux postes dans les services. | I10: Appel
B11: ✅ | C11: T1-8 | D11: Structurant | E11: Responsable imagerie | F11: CCOPS CHOR | G11: Ralentissement PACS | H11: Bonjour, je vous appelle parce qu'il semblerait qu'il y ait un ralentissement du PACS. On a de plus en plus de mal à pouvoir consulter les résultats d'imagerie, c'est vraiment contraignant. A ce rythme là, on devra bientôt se déplacer pour les consulter directement sur les appareils d'imagerie. On perd un temps fou ! | I11: Appel
B12: ✅ | C12: T1-9 | D12: Structurant | E12: ADVENS (PRIS) | F12: CCOPS CHU | G12: Le SOC EDR (opéré par ADVENS en métropole) remonte des alertes au CHU | H12: Objet : EXERCICE EXERCICE EXERCICE - Alerte SOC EDR - Activité suspecte détectée Bonjour, L'EDR a détecté une activité suspecte sur plusieurs systèmes. Il semble qu'un processus Windows légitime ait été lancé et ait établi des connexions réseau avec une adresse IP externe. Nous poursuivons les investigations. Cordialement, ADVENS | I12: E-mail
B13: ✅ | C13: T1-10 | D13: Saturant | E13: Service juridique | F13: CCD CHU | G13: Fichier qui ne s'ouvre pas au service juridique | H13: Bonsoir, j'ai besoin d'accéder à mon rapport d'investigation de la semaine dernière, mais sa lecture est impossible depuis mon PC. Le Procureur donne suite au dépôt de plainte d'une interne en cardiologie et j'ai besoin d'y accéder d'ici demain matin. | I13: Appel
B14: ✅ | C14: T1-11 | D14: Structurant | E14: Chef de service des urgences | F14: CCOPS CHU | G14: Ralentissements postes de travail | H14: Bonjour, les PC sont de plus en plus lents. On essaie de les redémarrer mais c'est vraiment laborieux. Que se passe-t-il ? | I14: Appel
B15: ✅ | C15: T1-12 | D15: Structurant | E15: Médecin | F15: CCOPS CHOR | G15: Perte accès au PACS | H15: Bonjour, Je vous appelle parce que nous n'arrivons plus à accéder aux images du PACS. Impossible d'accéder à l'historique des images du dossier, ça charge en boucle… | I15: Appel
B16: ✅ | C16: T1-13 | D16: Structurant | E16: Médecin | F16: CCOPS CHU | G16: Perte accès au PACS | H16: Bonjour, Je vous appelle parce que nous n'arrivons plus à accéder aux images du PACS. Impossible d'accéder à l'historique des images du dossier, ça charge en boucle… | I16: Appel
B17: ✅ | C17: T1-14 | D17: Structurant | E17: Cadre de santé | F17: CCD CHU | G17: Perte accès calendrier Outlook | H17: Bonjour, j'ai essayé d'accéder au calendrier Outlook mais impossible de le consulter. Même problème sur les différents PC du service, comment peut-on y accéder ? | I17: Appel
B18: ✅ | C18: T1-15 | D18: Structurant | E18: Responsable laboratoire | F18: CCD CHU | G18: Robot du laboratoire en panne | H18: Bonjour, on a une panne au niveau des laboratoires de biologie. Les étiquettes ne sortent pas, nous sommes passés en mode dégradé. Nous prenons du retard, nous tentons tout de même de transmettre les résultats les plus urgents | I18: E-mail
B19: ✅ | C19: T1-16 | D19: Structurant | E19: Responsable laboratoire | F19: CCD CHOR | G19: Robot du laboratoire en panne | H19: Bonjour, on a une panne au niveau des laboratoires de biologie. Les étiquettes ne sortent pas, nous sommes passés en mode dégradé. Nous prenons du retard, nous tentons tout de même de transmettre les résultats les plus urgents | I19: E-mail
B20: ✅ | C20: T1-17 | D20: Structurant | E20: Secrétaire médicale | F20: CCOPS CHU | G20: ="Bug de "&Applicatifs!$B$12&" (Gestion des plannings)" -> Bug de Logiciel de gestion des plannings (Gestion des plannings) | H20: ="Bonjour, c'est X qui vous contacte, on m'a informé qu'en plus de "&Applicatifs!$B$5&" il y a un bug sur "&Applicatifs!$B$12&". On n'a plus aucune visibilité sur les plannings, il y a une page blanche qui s'affiche sans aucun contenu, est-ce que c'est normal ?" -> Bonjour, c'est X qui vous contacte, on m'a informé qu'en plus de Pastel il y a un bug sur Logiciel de gestion des plannings. On n'a plus aucune visibilité sur les plannings, il y a une page blanche qui s'affiche sans aucun contenu, est-ce que c'est normal ? | I20: Appel
B21: ✅ | C21: T1-18 | D21: Structurant | E21: Chef de service réanimation | F21: CCD CHU | G21: Perte du monitoring | H21: Bonjour, je viens de m'apercevoir que les paramètres vitaux de nos patients sont figés sur l'écran de la salle de monitoring depuis un quart d'heure. On est obligés d'aller de chambre en chambre pour les surveiller. Est-ce qu'un technicien peut intervenir en urgence s'il vous plait ? | I21: Appel
B22: ✅ | C22: T1-19 | D22: Saturant | E22: Responsable maternité | F22: CCOPS CHU | G22: Fichier qui ne s'ouvre pas en maternité | H22: Bonsoir, j'essaye d'ouvrir un fichier excel depuis mon poste, mais mon PC m'indique que je ne peux pas l'ouvrir. Tout marchait pourtant très bien la dernière fois que je l'ai ouvert. Est-ce que vous pouvez me réinstaller Excel sur le PC ? | I22: Appel
B23: ✅ | C23: T1-20 | D23: Structurant | E23: Responsable laboratoire | F23: CCD CHU | G23: ="Bug de "&Applicatifs!$B$15&" (Gestion de la température)" -> Bug de Logiciel de gestion de la température (Laboratoire) (Gestion de la température) | H23: Bonjour, on est très inquiet au laboratoire, on vient de voir que le logiciel de gestion de la température ne fonctionnait pas cette nuit. La direction des services technique n'arrive pas a identifier le problème et on a aucun moyen de savoir si les frigos ont été maintenus à la bonne température. Ça pose un gros problème pour les poches sanguines, on ne sait pas quoi faire là. | I23: Appel
B24: ✅ | C24: T1-21 | D24: Structurant | E24: Responsable pharmacie | F24: CCOPS CHU | G24: ="Problème "&Applicatifs!$B$13&" (Gestion des stocks)" -> Problème Pharma® (Gestion des stocks) | H24: ="Bonjour, on vous contacte car depuis ce matin "&Applicatifs!$B$13&" est très lent depuis ce matin... Cela pèse sur le fonctionnement de la pharmacie car on tourne au ralenti. Savez-vous ce qu'il en est ?" -> Bonjour, on vous contacte car depuis ce matin Pharma® est très lent depuis ce matin... Cela pèse sur le fonctionnement de la pharmacie car on tourne au ralenti. Savez-vous ce qu'il en est ? | I24: Appel
B25: ✅ | C25: T1-22 | D25: Structurant | E25: Responsable laboratoire | F25: CCD CHOR | G25: ="Bug de "&Applicatifs!$B$15&" (Gestion de la température)" -> Bug de Logiciel de gestion de la température (Laboratoire) (Gestion de la température) | H25: Bonjour, on est très inquiet au laboratoire, on vient de voir que le logiciel de gestion de la température ne fonctionnait pas cette nuit. La direction des services technique n'arrive pas a identifier le problème et on a aucun moyen de savoir si les frigos ont été maintenus à la bonne température. Ça pose un gros problème pour les poches sanguines, on ne sait pas quoi faire là. | I25: Appel
B26: ✅ | C26: T1-23 | D26: Structurant | E26: Responsable pharmacie | F26: CCOPS CHOR | G26: ="Problème "&Applicatifs!$B$13&" (Gestion des stocks)" -> Problème Pharma® (Gestion des stocks) | H26: ="Bonjour, on vous contacte car depuis ce matin "&Applicatifs!$B$13&" est très lent depuis ce matin... Cela pèse sur le fonctionnement de la pharmacie car on tourne au ralenti. Savez-vous ce qu'il en est ?" -> Bonjour, on vous contacte car depuis ce matin Pharma® est très lent depuis ce matin... Cela pèse sur le fonctionnement de la pharmacie car on tourne au ralenti. Savez-vous ce qu'il en est ? | I26: Appel
B27: ✅ | C27: T1-24 | D27: Saturant | E27: Secrétaire médicale | F27: CCOPS CHU | G27: Les postes informatiques des admissions ne répondent plus | H27: Bonjour, je vous contacte en urgence car la GAM ne répond plus sur tous les postes informatiques au niveau du guichet des admissions aux urgences. Nous continuons de traiter les demandes en manuscrit mais ça ne va pas être possible indéfiniment, ça prend beaucoup de temps et nous sommes de plus en plus saturés. | I27: Appel
B28: ✅ | C28: T1-25 | D28: Structurant | E28: Prestataire biomédical - BioCom | F28: CC Biomédicale CHU Sud | G28: Alerte compromission SI prestataire biomédical | H28: Bonjour, Nous vous contactons car nous avons constaté des potentiels accès suspects à des données de nos comptes clients en date du 6 janvier. Nos équipes sont pleinement mobilisées sur les investigations. Pour l'heure nous n'avons pas de raison de penser que des accès de maintenance aient pu être compromis. Néanmoins dans un souci de transparence, nous souhaitions vous tenir informés de cette situation et nous vous tiendrons au courant des résultats de nos investigations. | I28: E-mail
B29: ✅ | C29: T1-26 | D29: Structurant | E29: Prestataire biomédical - BioCom | F29: CCOPS CHOR | G29: Alerte compromission SI prestataire biomédical | H29: Bonjour, Nous vous contactons car nous avons constaté des potentiels accès suspects à des données de nos comptes clients en date du 6 janvier. Nos équipes sont pleinement mobilisées sur les investigations. Pour l'heure nous n'avons pas de raison de penser que des accès de maintenance aient pu être compromis. Néanmoins dans un souci de transparence, nous souhaitions vous tenir informés de cette situation et nous vous tiendrons au courant des résultats de nos investigations. | I29: E-mail
B30: ✅ | C30: T1-27 | D30: Structurant | E30: Médecin | F30: CCD CHU | G30: ="Problème DPI : "&Applicatifs!$B$4&" inaccessible" -> Problème DPI : CrossWay inaccessible | H30: =Applicatifs!$B$4&" c'est une catastrophe depuis ce matin, ça rame beaucoup, un coup il s'ouvre, un coup il ne s'ouvre pas…" -> CrossWay c'est une catastrophe depuis ce matin, ça rame beaucoup, un coup il s'ouvre, un coup il ne s'ouvre pas… | I30: Appel
B31: ✅ | C31: T1-28 | D31: Structurant | E31: Cadre de santé | F31: CCOPS CHU | G31: Problème remontée PACS | H31: Je ne comprends, pas les résultats ne remontent pas dans le DPI alors que le labo m'a dit que les résultats étaient envoyés depuis 1 heure ! | I31: Appel
B32: ✅ | C32: T1-29 | D32: Saturant | E32: Chef de service des urgences | F32: CCD CHU | G32: Plainte de l'accueil des urgences qui ne reçoivent pas les résultats du laboratoire | H32: C'est l'accueil des urgences qui vous rappelle, nous n'avons pas les résultats du laboratoire donc c'est assez problématique. Nous nous retrouvons surchargés par les différents problèmes depuis ce matin, il faut à tout prix nous donner des explications et directives. Nous n'arrivons pas à joindre le laboratoire. | I32: Appel
B33: ✅ | C33: T1-30 | D33: Saturant | E33: Cadre de santé | F33: CCOPS CHU | G33: Impression non-stop de test d'encre | H33: Bonjour, j'ai voulu imprimer le calendrier des gardes administratives en trois exemplaires, mais l'imprimante continue à imprimer des feuilles avec des tests d'encre. J'ai du faire une fausse manipulation. Je l'ai débranchée et ça continue. Vous pouvez passez la voir quand vous avez un moment ? Parce que je ne sais pas comment l'arrêter autrement. | I33: Appel
B34: ✅ | C34: T1-31 | D34: Structurant | E34: ADVENS (PRIS) | F34: CCOPS CHOR | G34: Remontée d'alerte CHOR | H34: Bonjour, nous vous remontons une alerte concernant la création de comptes administrateurs et d'élévations de privilège qui semblent coincider avec l'incident en cours au CHU. Les serveurs et postes du CHOR ne sont pas compromis et aucune trace d'exfiltration ou de chiffrement pour le moment. Nous surveillons et continuons d'investiguer. | I34: Appel
B35: ✅ | C35: T1-32 | D35: Saturant | E35: Chargée de communication | F35: CCOPS CHU | G35: Email de phishing déjoué par un agent vigilant | H35: Bonjour, j'ai reçu cet email en pièce-jointe, je pense qu'il s'agit d'une tentative de phishing, mieux vaut prévenir les autres ! Bonne journée, | I35: E-mail
B36: ✅ | C36: T1-33 | D36: Saturant | E36: Chargée de communication | F36: CCOPS CHOR | G36: Email de phishing déjoué par un agent vigilant | H36: Bonjour, j'ai reçu cet email en pièce-jointe, je pense qu'il s'agit d'une tentative de phishing, mieux vaut prévenir les autres ! Bonne journée, | I36: E-mail
B37: ✅ | C37: T1-34 | D37: Saturant | E37: Chef de service cardiologie | F37: CCD CHU | G37: Chirurgien du service de chirurgie cardiaque et vasculaire ne parvient pas à ouvrir son fichier pour accéder au programme opératoire de la semaine | H37: Bonjour, j'essaye depuis un quart d'heure d'ouvrir le fichier pour accéder au programme opératoire. Pourriez-vous m'aider à résoudre le problème ? J'ai pourtant une bonne connexion. En attendant, il me semble qu'une IDE édite le progamme opératoire tous les jours sur support papier. Je vais essayer de retrouver qui c'est. | I37: Appel
B38: ✅ | C38: T1-35 | D38: Structurant | E38: Chef de service réanimation | F38: CCD CHU | G38: Problème en réanimation sur Ré@ssist (logiciel réa) | H38: Bonjour les équipes de réanimation m'ont contacté : apparement le logiciel Ré@ssist n'est pas accessible, ils ne peuvent plus mettre à jour les données des patients, ils passent en mode dégradé, mais nous avons des patients critiques pour qui nous ne pouvons pas nous permettre de perdre même momentanément des données essentielles à la prise en charge. | I38: Appel
B39: ✅ | C39: T1-36 | D39: Structurant | E39: Cadre de santé | F39: CCD CHU | G39: Dysfonctionnement Chauffage Ventilation Clim (CVC) | H39: Bonjour, la climatisation ne fonctionne plus, vous avez prévu d'envoyer des techniciens ? | I39: Appel
B40: ✅ | C40: T1-37 | D40: Saturant | E40: Responsable RH | F40: CCOPS CHU | G40: Fichier .txt qui apparaît de manière incontrolable | H40: Bonsoir, j'ai un bug avec le PC de la pharmacie, au niveau de la zone de préparation. J'ai un document qui n'arrête pas de surgir, même si je le ferme. Est-ce que je peux redémarrer le PC ? | I40: Appel
B41: ✅ | C41: T1-38 | D41: Saturant | E41: Cadre de santé | F41: CCD CHU | G41: Plainte de plusieurs services qui ne reçoivent pas les résultats du laboratoire | H41: C'est le service X qui vous appelle, nous n'avons pas les résultats du laboratoire donc c'est assez problématique, nous nous retrouvons surchargés par les différents problèmes. Il faut à tout prix nous donner des explications et directives. Nous n'arrivons pas à joindre le labo. | I41: Appel
B42: ✅ | C42: T1-39 | D42: Saturant | E42: Cadre de santé | F42: CCOPS CHU | G42: Plainte de plusieurs services qui ne reçoivent pas les résultats du laboratoire | H42: C'est le service X qui vous appelle, nous n'avons pas les résultats du laboratoire donc c'est assez problématique, nous nous retrouvons surchargés par les différents problèmes.. il faut à tout prix nous donner des explications et directives. Nous n'arrivons pas à joindre le labo. | I42: Appel
... B50: ❌ | C50: T1-47 | D50: Structurant | E50: Chef de service des urgences | F50: CCD CHU | G50: Chirurgie besoin des résultats | H50: Bonjour, On a beaucoup de patients qui sortent du bloc actuellement. Nous avons besoin de résultats d'analyse, d'imagerie mais rien ne fonctionne on dirait. Nous n'avons même plus accès au DPI. | I50: Appel
B51: Tango 2 - Plan de sauvegarde
B52: ❌ | C52: T2-1 | D52: Structurant | E52: CERT SANTE | F52: CCD CHU | G52: Accusé de réception de déclaration d'incident | H52: Bonjour, Nous accusons réception de la déclaration d’incident déposée sur le portail des évènements sanitaires indésirables ce jour par le directeur de votre structure. Nous avons bien noté que vous bénéficiez de l'accompagnement d'ADVENS dans ce contexte. Suite à l’analyse de votre déclaration, pourriez-vous nous apporter des précisions quant au périmètre concerné par l'attaque? Nous vous demandons de bien vouloir nous tenir informés de l’évolution de la situation et revenons vers vous rapidement pour effectuer de premières investigations. Cordialement, CERT Santé cyberveille@esante.gouv.fr | I52: E-mail
B53: ❌ | C53: T2-2 | D53: Structurant | E53: CORRUSS | F53: ARS | G53: Demande de point de situation | H53: [Si CORRUSS prévenu par l'ARS] Bonjour, ici le centre de veille du CORRUSS nous avons été alerté par le HFDS du ministère qu'une cyberattaque touchait actuellement le CHU de la Réunion. L'offre de soins territoriale de la Réunion exige la prudence. Nous voudrions que vous nous fassiez un point de situation d'ici trente minutes concernant : - Le périmètre de l'attaque (CHU ou GHT ?) - Les impacts potentiels sur l'offre de soins territoriale, la prise en charge et le suivi des patients - Les mesures que vous comptez mettre en place à l'échelle de l'agence et celles en coordination avec la Préfecture Je vous propose de me faire ce retour par email et en fonction, je vous recontacterai. | I53: Appel
B54: ✅ | C54: T2-3 | D54: Structurant | E54: SAMU | F54: Préfecture | G54: Alerte régulation du SAMU et embouteillages | H54: [Si transfert de patients vers le CHOR/GHER] Bonjour, ici le SAMU, les axes routiers en périphérie et au centre de Saint-Denis sont particulièrement saturés, les voitures sont à l'arrêt, on a vraiment des difficultés à passer pour transférer les patients vers le CHOR (ou GHER). Le temps de transfert, sans compter, les flux entrants habituels, sont doublés, on aurait besoin de l'appui des forces de l'ordre pour sécuriser et faciliter notre passage. L'accident de ce midi en aval du giratoire de Gillot en direction de La Ressource à Sainte-Marie n'arrange rien, il y a des véhicules gravement endommagé (VGE), c'est une situation critique. Nous attendons une intervention et le remorquage des véhicules. | I54: Appel
B55: ❌ | C55: T2-4 | D55: Structurant | E55: Accueil | F55: CCD CHU | G55: Engorgement de la ligne de l'accueil du CHU | H55: [Uniquement si le réseau du CHU n'est pas encore isolé] Bonjour, je vous appelle de l'accueil nous sommes complètement saturés par les appels de personnes voulant savoir si elles peuvent se rendre à l'hôpital. Il y aurait des informations relayées par les patients sur les réseaux sociaux indiquant que les services du CHU sont dépassés par les événements. La téléphonie de l'hôpital est hors service donc ils passent tous par nous et on risque de rater de vraies urgences. | I55: Appel
B56: ✅ | C56: T2-5 | D56: Saturant | E56: IMAZPRESS | F56: CCD CHU | G56: Appel journaliste vers la CCH | H56: Bonjour, je suis journaliste chez IMAZPRESS, sur les réseaux nous voyons beaucoup de choses passer concernant le CHU, est-ce qu'on peut s'y rendre pour se faire soigner? Quel est le problème ? Certains parlent d'un problème informatique... C'est une cyberattaque? Pourquoi la population n'est au courant de rien ? | I56: Appel
B57: ❌ | C57: T2-6 | D57: Saturant | E57: ZINFOS 974 | F57: Préfecture | G57: Appel journaliste vers le service communication | H57: Bonjour, je suis journaliste chez ZINFOS 974, sur les réseaux nous voyons beaucoup de choses passer concernant le CHU, est-ce qu'on peut s'y rendre pour se faire soigner? Quel est le problème ? Certains parlent d'un problème informatique... C'est une cyberattaque? Pourquoi la population n'est au courant de rien ? | I57: Appel
B58: ❌ | C58: T2-7 | D58: Structurant | E58: Officier CODIS 974 | F58: Préfecture | G58: Remontée d'alerte à la préfecture | H58: [Si CODIS prévenu par le CHU] Le CHU de la Réunion vient de nous informer qu'ils subissaient potentiellement une cyberattaque, en prévention, ils nous indiquent qu'ils vont probablement rencontrer des difficultés à prendre en charge le flux habituel de patients au niveau du SAU. Un risque d'engorgement est à anticiper. | I58: Appel
B59: ✅ | C59: T2-8 | D59: Structurant | E59: Cadre de santé | F59: CCD CHU | G59: PC de secours chiffrés | H59: [Si PC de secours déployés au CHU] Bonjour, A la suite du dysfonctionnement DPI nous venons d'allumer le poste de secours et l'écran reste bloqué tout en noir avec une horloge qui tourne. | I59: Appel
B60: ✅ | C60: T2-9 | D60: Structurant | E60: Infirmière | F60: CCD CHU | G60: Ne trouve pas le PC de secours | H60: [Si PC de secours déployés au CHU] Bonjour, Je suis infirmière en médecine interne. On nous demande de passer en mode dégradé mais comment on fait ?? Il n'y a pas de PC de secours. | I60: Appel
B61: ✅ | C61: T2-10 | D61: Saturant | E61: Linfo.re | F61: ARS | G61: Appel journaliste vers le service communication | H61: Bonjour, je suis journaliste chez Linfo.re, sur les réseaux nous voyons beaucoup de choses passer concernant le CHU, est-ce qu'on peut s'y rendre pour se faire soigner? Quel est le problème ? Certains parlent d'un problème informatique... C'est une cyberattaque? Pourquoi la population n'est au courant de rien ? | I61: Appel
B62: ❌ | C62: T2-11 | D62: Structurant | E62: SAMU | F62: Préfecture | G62: Alerte régulation du SAMU et embouteillages | H62: Bonjour, ici le SAMU, les axes routiers en périphérie et au centre de Saint-Denis sont particulièrement saturés, les voitures sont à l'arrêt, on a vraiment des difficultés à passer pour transférer les patients vers le CHOR. Le temps de transfert, sans compter, les flux entrants habituels, sont doublés, on aurait besoin de l'appui des forces de l'ordre pour sécuriser et faciliter notre passage. | I62: Appel
B63: ✅ | C63: T2-12 | D63: Structurant | E63: SAMU | F63: ARS | G63: Alerte régulation du SAMU et embouteillages | H63: Bonjour, ici la régulation du SAMU, les axes routiers en périphérie et au centre de Saint-Denis sont particulièrement saturés, les voitures sont à l'arrêt, on a vraiment des difficultés à passer pour transférer les patients vers le CHOR. On a prévenu la Préfecture mais le temps de transfert, sans compter, les flux entrants habituels, sont doublés, on aurait besoin de mobiliser davantage d'ambulances privées et on ne peut pas être sur tous les fronts, on a besoin que vous vous en occupiez. | I63: Appel
... B72: ❌ | C72: T2-21 | D72: Structurant | E72: Centre pénitentier de Saint-Denis - Directeur de la prison | F72: Préfecture | G72: Unité sanitaire en milieu pénitentiaire (USMP) ne fonctionne plus | H72: Bonjour, ici le directeur du centre pénitentiaire de Saint-Denis, le système d'information de l'unité sanitaire est rattachée au CHU, elle n'a plus accès au dossier patient informatisé et ne dispose pas des stocks de médicaments nécessaires. L'unité sanitaire de la prison n'est pas opérationnelle sans système d'information, quelle est la procédure dans ce cas de figure? On a posé la question à l'ARS et on attend un retour concernant la procédure de leur part. | I72: Appel
B73: ❌ | C73: T2-22 | D73: Structurant | E73: Journaliste | G73: Pression médiatique simulée (PMS) - Fake news sur la cyberattaque | H73: Bonjour, Jeanne Hoarau, journaliste pour le JIR (Journal de l'île de la réunion), nous apprenons qu'une vaste cyberattaque toucherait l'ensemble des hôpitaux de la Réunion. Pouvez-vous nous confirmer cette information? Qu'en est-il de la sécurité des populations ? Que fait l'Etat? Organisez vous des transferts? C'est une situation plus que périlleuse et rien n'est communiqué, ce n'est pas normal. Si vous ne souhaitez pas nous répondre, nous devrons faire avec les témoignages des patients et ce n'est pas glorieux pour l'image de l'administration si vous voulez tout savoir, sachant que ce n'est pas la première fois ! | I73: Appel
B74: ❌ | C74: T2-23 | D74: Structurant | E74: SAMU | F74: Préfecture | G74: Engorgement du Centre de Réception et de Régulation des Appels SAMU 15 (CRRA) | H74: Bonjour, ici le Centre de Réception et de Régulation des Appels du SAMU, notre plateforme d'appel est complètement saturée par les appels de personnes voulant savoir si elles peuvent se rendre à l'hôpital. Il y aurait des informations relayées par les patients sur les réseaux sociaux indiquant que les services du CHU sont dépassés par les événements. La téléphonie de l'hôpital est hors service donc ils passent tous par nous et on risque de rater de vraies urgences. | I74: Appel
B75: ❌ | C75: T2-24 | D75: Saturant | E75: EFS | F75: ARS | G75: Coupure des flux informatiques avec le CHU | H75: Bonjour, nous vous informons que nous avons pris des dispositions pour éviter toute propagation de la cyberattaque vers notre structure. Nous avons pris la décision de couper les échanges de données informatisés (EDI) avec le CHU. | I75: E-mail
B76: Fin de J1 - Début J2
B77: ✅ | C77: T2-25 | D77: Structurant | E77: Responsable pharmacie | F77: CCD CHU | G77: Alerte sur la désorganisation | H77: Bonjour, nous venons de nous rendre compte que nous avons interverti le traitement de deux patients par erreur. Nous avons des difficultés à gérer le mode papier et craignons que d'autres erreurs soient réalisées. Quelle organisation pouvons-nous mettre en place pour éviter ces erreurs ? | I77: Appel
B78: ❌ | C78: T2-26 | D78: Saturant | E78: Ministère de la justice | F78: Préfecture | G78: Coupure des flux informatiques avec le CHU (A valider avec Djamil) | H78: Bonjour, nous vous informons que nous avons pris des dispositions pour éviter toute propagation de la cyberattaque vers notre structure. Nous avons pris la décision de couper les échanges de données informatisés (EDI) avec le CHU. | I78: E-mail
B79: ✅ | C79: T2-27 | D79: Saturant | E79: SAMU | F79: ARS | G79: Inquiétude | H79: Bonjour, on a reçu un appel d'une femme dont le mari a été admis aux urgences du CHU Nord ce matin. C'est bien nous qui l'avons transféré aux urgences du CHU mais le problème c'est que si il a été retransféré quelque part, on n'a pas l'info. On reçoit plusieurs appels dans ce sens mais on ne sait pas quoi leur dire. Il faudrait mettre en place un suivi des transferts et rassurer les familles rapidement. | I79: Appel
B80: ✅ | C80: T2-28 | D80: Structurant | E80: SAMU | F80: ARS | G80: Ralentissements sur le logiciel de régulation médicale | H80: Bonjour, au niveau du CRRA (Centre de Réception et de Régulation des Appels SAMU 15), on a de gros ralentissements au niveau du logiciel de régulation médicale. Les données ne s'incorporent qu'au bout d'une minute. On a déjà eu ce genre de ralentissements, mais comme nous ne savons pas combien de temps ces derniers vont durer, on est passé sur nos fiches pré-remplies papier pour ne perdre aucune info. On revient vers vous dès qu'on en sait plus sur les délais de rétablissements de ce ralentissement. | I80: Appel
B81: ❌ | C81: T2-29 | D81: Saturant | E81: EDF | F81: Préfecture | G81: Coupure des flux informatiques avec le CHU (A valider avec Djamil) | H81: Bonjour, nous vous informons que nous avons pris des dispositions pour éviter toute propagation de la cyberattaque vers notre structure. Nous avons pris la décision de couper les échanges de données informatisés (EDI) avec le CHU. | I81: E-mail
B82: ❌ | C82: T2-30 | D82: Saturant | E82: Responsable service batimentaire | F82: CCD CHU | G82: Panne ascenseur | H82: Bonjour nous avons une panne d'ascenseur, nous souhaitons rapidement régler le problème mais nous n'arrivons pas à identifier pour l'instant le problème et nous ne savons pas combien de temps cela prendra pour réparer.. | I82: E-mail
B83: ❌ | C83: T2-31 | D83: Saturant | E83: Infirmière | F83: CCD CHU | G83: Fugue d'un patient | H83: Bonjour, un patient est introuvable depuis plus d'une heure. Cela nous préoccupe beaucoup, il est particulièrement instable. | I83: Appel
B84: ✅ | C84: T2-32 | D84: Saturant | E84: Infirmière | F84: CCD CHOR | G84: Fugue d'un patient à l'EPSMR | H84: Bonjour, un patient est introuvable depuis plus d'une heure. Cela nous préoccupe beaucoup, il est particulièrement instable. | I84: Appel
B85: ❌ | C85: T2-33 | D85: Structurant | E85: Cadre de santé | F85: CCD CHU | G85: Cadre inquiet à propos des informations qui fuitent sur les problèmes informatiques | H85: Bonjour, je suis cadre aux urgences, je me permets de vous contacter directement car j'ai un patient ce matin aux urgences qui est journaliste, et comme depuis ce matin il a pu entendre qu'on rencontre des problèmes informatiques, il arrête pas de me poser des question ainsi qu'aux autres urgentistes. Je crains qu'il transmette de fausses informations ou que cela soit divulgué | I85: Appel
B86: ❌ | C86: T2-34 | D86: Saturant | E86: Chef de service cardiologie | F86: CCD CHU | G86: Responsable d’un service en congé | H86: Bonjour, nous avons une opération très importante de programmée aujourd'hui pour un patient dont l'état se dégrade rapidement, on doit le transférer dans un autre établissement au plus vite ! | I86: E-mail
B87: ❌ | C87: T2-35 | D87: Structurant | E87: ADVENS (PRIS) | F87: CCOPS CHU | G87: Avancée des investigations | H87: Bonjour, D'après nos analyses, les contrôleurs de domaines ont été compromis et sont partiellement chiffrés. Serveur de messagerie et mails sont compromis. Nous n'avons pas pu établir un pourcentage exact de toutes les machines chiffrées. Nous ne pouvons pas accéder aux sauvegardes, le serveur permettant de les lire a été chiffré. Nous ne sommes pas capable de préciser l'état des sauvegardes pour le moment. | I87: Appel
B88: ✅ | C88: T2-36 | D88: Saturant | E88: Chef de service des urgences | F88: CCD CHU | G88: Journalistes aux urgences | H88: Bonsoir, Il semblerait qu'il y avait un journaliste par hasard aux urgences cette nuit. Il a posé beaucoup de questions sur ce qu'il se passe actuellement à l'hôpital. Ne faudrait-il pas communiquer avant que ce journaliste des informations? | I88: E-mail
... B92: ✅ | C92: T2-40 | D92: Saturant | E92: Psychiatrie | F92: CCD CHU | G92: Fugue d'un patient en psychiatrie | H92: Un patient avec des troubles psychotiques a fugué. Il a lancé un pied à perfusion sur l'IDE de nuit et s'est enfui. Nous avons prévenu sa famille. Pourriez-vous prévenir tous les service avec son signalement ? Sans annuaire et sans possibilité d'utiliser nos mails, difficile de faire passer l'information. Et j'y pense, vous pouvez voir avec la sécurité si ils peuvent visionner les images des caméras de surveillance ? Merci (si description demandée : jeune de 19 ans, short de sport de basket noir, marcel gris, cheveux brun court, 1m70, fin) | I92: Appel
B93: Tango 3 - Aggravation de la situation
B94: ❌ | C94: T3-2 | D94: Structurant | E94: Responsable RH | F94: CCD CHU | G94: Panne logiciels RH | H94: Bonjour, nous n'avons pas beaucoup de stocks de courriers, contrats et avenants papiers, nous allons vite être à court… Nos équipes sont démotivées, on ne peut pas travailler sans nos logiciels… | I94: Appel
B95: ❌ | C95: T3-3 | D95: Structurant | E95: Centre pénitentier de Saint-Denis - Directeur de la prison | F95: Préfecture | G95: Unité sanitaire en milieu pénitentiaire (USMP) ne fonctionne plus | H95: Bonjour, c'est à nouveau le directeur de la prison de Saint-Denis, nous n'avons eu aucun retour de votre part concernant l'unité sanitaire, je me répète mais certains des prisonniers ont besoins de traitement à périodicité régulière et d'un suivi, sauf que sans DPI, le médecin est aveugle. On a déjà un prisonnier dont l'état de santé s'est dégradé, on ne sait même pas si on peut encore les envoyer au CHU, on n'arrive pas à les joindre, la plateforme téléphonique du SAMU est saturée. Que devons nous faire ? | I95: Appel
B96: ✅ | C96: T3-4 | D96: Structurant | E96: Centre pénitentier de Saint-Denis - Directeur de la prison | F96: ARS | G96: Unité sanitaire en milieu pénitentiaire (USMP) ne fonctionne plus | H96: Bonjour, c'est à nouveau le directeur de la prison de Saint-Denis, nous n'avons eu aucun retour de votre part concernant l'unité sanitaire, je me répète mais certains des prisonniers ont besoins de traitement à périodicité régulière et d'un suivi, sauf que sans DPI, le médecin est aveugle. On a déjà un prisonnier dont l'état de santé s'est dégradé, on ne sait même pas si on peut encore les envoyer au CHU, on n'arrive pas à les joindre, la plateforme téléphonique du SAMU est saturée. Que devons nous faire ? | I96: Appel
B97: ❌ | C97: T3-5 | D97: Saturant | E97: Centre hospitalier de Mayotte | F97: ARS | G97: Evacuation sanitaire (EVASAN) - Chirurgie viscérale | H97: Bonjour, ici le centre hospitalier de Mayotte, nous aurions besoin de réaliser une évacuation sanitaire pour une intervention de chirurgie viscérale. Le patient souffre d'une hernie inguinale engouée mais nous n'avons plus de place ici. Il est actuellement aux urgences en attente d'un bloc. Le transfert est il possible à La Réunion ? Plusieurs confrères médecins du CHU de la Réunion nous ont prévenu de la cyberattaque qui les touche et nous ont transmis ce numéro car ce patient ne peut pas attendre. | I97: Appel
B98: ✅ | C98: T3-6 | D98: Structurant | E98: SMUR | F98: Préfecture | G98: Transfert sanitaire - 2 patients en réanimation victimes d'insuffisance respiratoire aiguë (IRA) | H98: Bonjour, Nous devons transférer deux patients hospitalisés en réanimation depuis le CHU. Les deux patients sont atteints d'une insuffisance respiratoire aiguë. Ils sont sous assistance respiratoire, mais suffisamment stables pour supporter un transport qui dure maximum 3h. Toutefois, tous nos véhicules terrestres sont en mission, ainsi que notre équipe hélismur. En plus, il y a beaucoup d'embouteillages à Saint-Denis Pourriez-vous nous aider à héliporter ces deux patients vers un autre établissement ? | I98: Appel
B99: ❌ | C99: T3-7 | D99: Structurant | E99: SAMU | F99: Préfecture | G99: Confirmation de non atteinte à l'infrastructure SI du SAMU | H99: Bonjour, Je vous confirme que l'infrastructure SI du SAMU n'est pas touché par la cyberattaque. | I99: E-mail
B100: ❌ | C100: T3-8 | D100: Structurant | E100: SAMU | F100: ARS | G100: Confirmation de non atteinte à l'infrastructure SI du SAMU | H100: Bonjour, Je vous confirme que l'infrastructure SI du SAMU n'est pas touché par la cyberattaque. | I100: E-mail
B101: ❌ | C101: T3-9 | D101: Structurant | E101: Ministère de la Santé | F101: ARS | G101: Demande de point de situation | H101: Bonjour, le directeur de cabinet du ministère du Travail, de la Santé et des Solidarités souhaiterait connaître les évolutions de la situation à J+1. Vous pouvez nous retourner par email un point de situation détaillant : - Le taux d'occupation global et par service impactés du CHU de la Réunion - Le taux d'occupation des urgences et services en tension des établissements de repli - Les besoins en effectifs - Les impacts avérés et potentiels sur le dispositif de santé territorial (en prenant en compte Mayotte) - Les actions engagées par l'ARS Pouvez-me faire ce retour écrit d'ici 20 minutes? C'est urgent, le directeur de cabinet voit le ministère dans moins d'une heure. | I101: Appel
B102: ❌ | C102: T3-10 | D102: Structurant | E102: Service des urgences - CHOR | F102: ARS | G102: Saturation des urgences | H102: [Si délestage des urgences du CHU vers le CHOR] Bonjour, Ici le chef de service des urgences du Centre Hospitalier Ouest Réunion (CHOR), le délestage des urgences du CHU vers notre structure impacte notre capacité de prise en charge. On a activé notre plan blanc comme demandé mais les urgences sont totalement saturées, le taux d'occupation était déjà élevé avant mais on pouvait gérer, nous avons de nombreuses urgences non traitées avec des patients qui attendent dans les couloirs, la salle d'attente est pleine et notre personnel commence à s'agacer. Combien de temps va durer la fermeture des urgences du CHU? Nous avons essayé de les joindre mais nous n'avons eu aucune réponse. On a besoin de visibilité ! | I102: Appel
B103: ✅ | C103: T3-11 | D103: Structurant | E103: Responsable pharmacie | F103: ARS | G103: Difficulté d'approvisionnement en médicaments | H103: Bonjour, Ici le chef de service de la pharmacie, nous avons perdu l'accès à notre annuaire de fournisseurs habituels, en anticipation nous essayons d'en contacter par téléphone à défaut de pouvoir passer par le circuit habituel. Cela exige un temps fou, nous en sommes au stade de vider notre stocker pour comptabiliser les réserves de médicaments, de plus certains de nos patients ont un traitement lourd et très spécifique à périodicité régulière (4 fois par jour). Nous aurions besoin de votre aide sur deux axes : - du personnel supplémentaire pour palier à l'activation de la procédure manuelle - une liste la plus exhaustive possible de fournisseurs en médicaments et en fournitures médicales type dispositif médicaux Pensez vous pouvoir nous aider? | I103: Appel
B104: ✅ | C104: T3-12 | D104: Structurant | E104: Ministère de l'intérieur et des Outre-mer - cabinet de la direction générale des Outre-mer | F104: Préfecture | G104: Demande de point de situation | H104: Bonjour, La cheffe de cabinet adjoint du ministre de l'Inérieur et des Outre-mer etl e Directeur de cabinet m'ont demandé de vous contacter pour que vous nous fassiez un point de situation d'ici une vingtaine 45 minutes concernant : - Le périmètre de l'attaque et son évolution - Les impacts effectifs et potentiels sur les enjeux de sécurité civile - Les mesures mises en place Ce retour doit être horodaté. Merci. Je vous propose de me faire ce retour par email et en fonction, je vous recontacterai. | I104: Appel
B105: ❌ | C105: T3-13 | D105: Structurant | E105: Forces de l'ordre | F105: Préfecture | G105: Risque blocage des routes par les manifestations des acteurs du BTP | H105: Nous constatons une propagation du mouvement des professionnels du BTP en colère de la métropole vers l'île, avec certains premiers blocus par des véhicules agricoles sur certaines routes. Nous ne savons pas si le mouvement va réellement prendre sur l'île mais nous devons anticiper le risque que de nombreuses routes soient bloquées par ces manifestants, ce qui impactera considérablement la circulation déjà toujours très dense habituellement. | I105: Appel
B106: ❌ | C106: T3-14 | D106: Saturant | E106: Météo France Réunion | F106: Préfecture | G106: Alerte sur les prévisions météo | H106: Bonjour, ici Météo France, nous vous remontons des risques cycloniques élevés sur la côte Nord-Est/Est de La Réunion dans un délai d'environ 7 jours. | I106: SMS
B107: ❌ | C107: T3-15 | D107: Structurant | E107: GRADeS Tesis | F107: CCOPS CHU | G107: Impacts Data Center | H107: Nous continuons les investigations avec l'aide de notre prestataire Nextira One ainsi qu'ADVENS. Nous vous tenons au courant dès que nous avons du nouveau de notre côté.
B108: ❌ | C108: T3-16 | D108: Structurant | E108: DG clinique privée | F108: ARS | G108: Point de situation | H108: Nous avons été contacté par des médecins du CHUR qui souhaitent organiser des transferts de patients directement avec nous. Nous souhaitons encadrer ces transferts avec vous car nous ne pouvons pas gérer au cas par cas les demandes de médecins qui s'appellent entre eux pour s'envoyer des patients même si c'est urgent. Nous avons besoin de connaître le nombre exact de patients qui doivent être transférés, pour quels types de soins, pour quels types d'interventions chirurgicales, si il y a une procédure d'identitovigilance de secours en cas de transfert de patients en l'absence de la GAM et du DPI ? | I108: Appel
B109: ❌ | C109: T3-17 | D109: Structurant | E109: CERT Santé | F109: CCOPS CHU | G109: Identifier un endroit sécurisé pour stocker les postes et serveurs compromis | H109: Identifier un endroit sécurisé pour stocker les postes et serveurs compromis | I109: Appel
B110: ❌ | C110: T3-18 | D110: Saturant | E110: Equipe opérationnelle d'hygiène CHU | F110: CCOPS CHU | G110: Appel du prestataire pour les DASRI | H110: Bonjour, les DASRI continuent à s'accumuler et le prestataire n'est pas venu depuis la semaine dernière. Quelqu'un a-t-il pensé à le rappeler entre temps ? Auriez vous son contact ? Ses coordonnées n'étaient que dans nos postes actuels indisponibles… | I110: Appel
B111: ❌ | C111: T3-19 | D111: Saturant | E111: Responsable RH | F111: CCD CHU | G111: Phishing déjoué par un agent vigilant | H111: Objet : EXERCICE EXERCICE EXERCICE - ALERTE campagne phishing Chers collègues, Je voulais vous informer d'une tentative de phishing que j'ai reçue aujourd'hui. L'e-mail semblait provenir de notre fournisseur de services de messagerie, mais après vérification, j'ai remarqué plusieurs signes révélateurs d'une tentative de phishing. L'e-mail demandait de vérifier les informations de mon compte en cliquant sur un lien. Cependant, en survolant le lien avec la souris, j'ai pu voir que l'URL ne correspondait pas à celle de notre fournisseur de services de messagerie. Je vous le signale donc par cet e-mail. Je n'ai évidemment cliqué sur aucun lien ni fourni d'informations personnelles. Nous devons rester vigilants face à ce type d'e-mails et à toujours vérifier les informations avant de cliquer sur des liens ou de fournir des informations personnelles. Cordialement, | I111: E-mail

Sheet ancien chrono
A2: Etat | B2: N° | C2: Horaire | D2: Type de stimuli | E2: Personnage | F2: Destinataire | G2: Objet | H2: Corps | I2: Personnage | J2: Modalité
A3: Tango 1
B4: 2 | D4: Structurant | G4: Dysfonctionnement des pneumatiques | H4: Bonjour, j'ai l'impression qu'il y a un dysfonctionnement avec les pneumatiques, plusieurs services se sont plaints de ne pas avoir les résultats du laboratoire. | I4: Equipe Technique | J4: Appel
B5: 3 | D5: Structurant | G5: Manque de personnel | H5: Bonjour, Il nous manque du personnel aujourd'hui. Nous ne serons pas en mesure d'assurer les transferts de patients... Les véhicules sont immobilisés. | I5: Responsable brancardage | J5: SMS
B6: 4 | D6: Structurant | G6: ="Dysfonctionnement "&Applicatifs!$B$5&" (Urgences)" -> Dysfonctionnement Pastel (Urgences) | H6: ="Bonjour, on constate sur le site un gros dysfonctionnement de "&Applicatifs!$B$5&" au niveau de l'accueil des urgences. Le logiciel tourne au ralenti et il y a beaucoup de personnes qui arrivent depuis ce matin, il y a de plus en plus d'attente…" -> Bonjour, on constate sur le site un gros dysfonctionnement de Pastel au niveau de l'accueil des urgences. Le logiciel tourne au ralenti et il y a beaucoup de personnes qui arrivent depuis ce matin, il y a de plus en plus d'attente… | I6: Accueil des urgences | J6: Appel
B7: 5 | D7: Structurant | G7: ="Dysfonctionnement "&Applicatifs!$B$5&" (Urgences)" -> Dysfonctionnement Pastel (Urgences) | H7: ="Bonjour, j'ai été contacté par X qui m'a dit qu'une fois de plus il y a de gros ralentissements sur "&Applicatifs!$B$5&" à l'accueil des urgences. X me demande ce qu'ils doivent faire. Merci." -> Bonjour, j'ai été contacté par X qui m'a dit qu'une fois de plus il y a de gros ralentissements sur Pastel à l'accueil des urgences. X me demande ce qu'ils doivent faire. Merci. | I7: Cadre des admissions | J7: Appel
B8: 6 | D8: Structurant | G8: ="Dysfonctionnement "&Applicatifs!$B$5&" (Urgences)" -> Dysfonctionnement Pastel (Urgences) | H8: ="Bonjour, je vous contacte car l'accueil des urgences commence à être saturé. On a des dysfonctionnements sur les postes informatiques, notamment des gros ralentissements de "&Applicatifs!$B$5&". Cela prend 3x plus de temps de créer les dossiers patients…" -> Bonjour, je vous contacte car l'accueil des urgences commence à être saturé. On a des dysfonctionnements sur les postes informatiques, notamment des gros ralentissements de Pastel. Cela prend 3x plus de temps de créer les dossiers patients… | I8: Accueil des urgences | J8: Appel
B9: 7 | D9: Structurant | G9: ="Dysfonctionnement "&Applicatifs!$B$5&" (Urgences)" -> Dysfonctionnement Pastel (Urgences) | H9: ="Bonjour, je suis cadre aux urgences. L'accueil des urgences nous ont dit qu'ils ont un problème informatique sur "&Applicatifs!$B$5&". Ça commence à être saturé et on a du mal à travailler. Vous savez quand le problème sera résolu ?" -> Bonjour, je suis cadre aux urgences. L'accueil des urgences nous ont dit qu'ils ont un problème informatique sur Pastel. Ça commence à être saturé et on a du mal à travailler. Vous savez quand le problème sera résolu ? | I9: Service des urgences | J9: Appel
B10: 8 | D10: Structurant | G10: ="Panne "&Applicatifs!$B$6&" (Laboratoire)" -> Panne INLOG (Laboratoire) | H10: ="Bonjour, il semblerait qu'il y ait une panne au niveau du laboratoire de biologie. "&Applicatifs!$B$6&" est en panne. On doit se déplacer pour avoir les résultats, c'est très long et on a beaucoup de mal à tenir le rythme." -> Bonjour, il semblerait qu'il y ait une panne au niveau du laboratoire de biologie. INLOG est en panne. On doit se déplacer pour avoir les résultats, c'est très long et on a beaucoup de mal à tenir le rythme. | I10: Service au choix | J10: Appel
B11: 9 | D11: Structurant | G11: Plainte de l'accueil des urgences qui ne reçoivent pas les résultats du laboratoire | H11: C'est l'accueil des urgences qui vous rappelle, nous n'avons pas les résultats du laboratoire donc c'est assez problématique. Nous nous retrouvons surchargés par les différents problèmes depuis ce matin, il faut à tout prix nous donner des explications et directives. Nous n'arrivons pas à joindre le laboratoire. | I11: Accueil des urgences | J11: Appel
B12: 10 | D12: Structurant | G12: Sous-effectif à l’hôpital | H12: Bonjour, Il nous manque du personnel ce matin. Nous avons tenté de contacter l'agence d'interim' mais ils ne repondent pas... Est-ce qu'on attend l'arrivée des cadres ? On essaie en parallèle de se réorganiser en interne pour assurer la continuité des soins mais nous ne sommes pas sûrs que ce soit possible. | I12: Service de cardiologie | J12: Appel
B13: 11 | D13: Structurant | G13: Appel stressé d’un soignant | H13: Bonjour, C'est l'heure de la relève, il manque du personnel, nous ne pouvons plus acceuillir les patients... Il me faut une place dès que possible ! En plus, l'armoire à pharmacie est capricieuse un coup elle s'ouvre un coup elle ne veut pas s'ouvrir... | I13: USIC | J13: Appel
B14: 13 | D14: Structurant | G14: ="Problème "&Applicatifs!$B$9&" (Gestion des repas)" -> Problème Logiciel de gestion des repas (Gestion des repas) | H14: ="Bonjour, il semblerait qu'il y ait un gros problème avec "&Applicatifs!$B$9&" ici, on n'arrive pas à se connecter et on ne peut pas servir les repas. Vous savez ce qu'il se passe ? Ça sera réparé dans combien de temps ?" -> Bonjour, il semblerait qu'il y ait un gros problème avec Logiciel de gestion des repas ici, on n'arrive pas à se connecter et on ne peut pas servir les repas. Vous savez ce qu'il se passe ? Ça sera réparé dans combien de temps ? | I14: Service de psychiatrie | J14: Appel
B15: 14 | D15: Structurant | G15: ="Problème "&Applicatifs!$B$9&" (Gestion des repas)" -> Problème Logiciel de gestion des repas (Gestion des repas) | H15: ="Bonjour, cela fait plus de 2h que nous attendons les repas, on vient d'enchaîner 4 accouchements en parallèle, comment vous dire que là ce n'est pas possible de continuer à travailler comme ça. Vous êtes sûrs qu'il n'y a pas un problème avec "&Applicatifs!$B$9&" ?" -> Bonjour, cela fait plus de 2h que nous attendons les repas, on vient d'enchaîner 4 accouchements en parallèle, comment vous dire que là ce n'est pas possible de continuer à travailler comme ça. Vous êtes sûrs qu'il n'y a pas un problème avec Logiciel de gestion des repas ? | I15: Service maternité | J15: Appel
B16: 15 | D16: Structurant | G16: ="Problème "&Applicatifs!$B$9&" (Gestion des repas)" -> Problème Logiciel de gestion des repas (Gestion des repas) | H16: Bonjour, c'est la médecine interne, est-ce que c'est la grève aujourd'hui ? Aucun repas n'est arrivé, il se passe quelque chose dont nous ne sommes pas au courant ? | I16: Service médecine interne | J16: Appel
B17: 16 | D17: Structurant | G17: ="Problème "&Applicatifs!$B$9&" (Gestion des repas)" -> Problème Logiciel de gestion des repas (Gestion des repas) | H17: ="Nous n'arrivons pas à accéder à "&Applicatifs!$B$9&", que faisons nous ? On doit servir les petits déjeuners !" -> Nous n'arrivons pas à accéder à Logiciel de gestion des repas, que faisons nous ? On doit servir les petits déjeuners ! | I17: Service de gériatrie | J17: Appel
B18: 17 | D18: Structurant | G18: ="Panne "&Applicatifs!$B$6&" (Laboratoire)" -> Panne INLOG (Laboratoire) | H18: ="Avez-vous du nouveau concernant les problèmes avec "&Applicatifs!$B$6&" ? C'est très problématique, avez-vous des infos svp ? Quand est-ce que ça sera réglé ?" -> Avez-vous du nouveau concernant les problèmes avec INLOG ? C'est très problématique, avez-vous des infos svp ? Quand est-ce que ça sera réglé ? | I18: Service au choix | J18: Appel
B19: 18 | D19: Structurant | G19: ="Dysfonctionnement "&Applicatifs!$B$10&" (Prescription)" -> Dysfonctionnement Logipren (Prescription) | H19: Improviser | I19: Service neonatalité | J19: Appel
B20: 19 | D20: Structurant | G20: L'administrateur de garde informe le DSI | H20: ="Bonjour, j'aimerais bien joindre le DSI pour lui faire un rapport sur les différentes informations que l'on m'a remonté : Dysfonctionnements de "&Applicatifs!$B$5&" à l'accueil des urgences, "&Applicatifs!$B$6&" hors service au laboratoire, "&Applicatifs!$B$9&" qui ne fonctionne plus…" -> Bonjour, j'aimerais bien joindre le DSI pour lui faire un rapport sur les différentes informations que l'on m'a remonté : Dysfonctionnements de Pastel à l'accueil des urgences, INLOG hors service au laboratoire, Logiciel de gestion des repas qui ne fonctionne plus… | I20: Administrateur de garde | J20: Appel
B21: 20 | D21: Structurant | G21: Appel des équipes de la DSI vers le DSI pour informer des difficultés | H21: Bonjour, on nous a remonté quelques pannes sur des logiciels,et le réseau est saturé depuis cette nuit. Ca doit générer des lenteurs. On ne comprends pas ce qu'il se passe pour le moment. | I21: Equipe DSI | J21: Appel
B22: 21 | D22: Structurant | G22: Appel de la cadre qui commence à être saturée de problématiques | H22: Bonjour, on me fait remonter des problèmes de toute part, je n'arrive plus à suivre et à tout faire remonter. Mon téléphone n'arrête pas de sonner et je n'ai pas le temps d'écouter ou de lire les messages qu'on me laisse.... C'est vraiment la folie aujourd'hui y'a rien qui va !!! | I22: Cadre de santé | J22: Appel
B23: 22 | D23: Structurant | G23: Ralentissement des distributeurs de linge | H23: Bonjour, service de médecine interne, nous avons du mal à récupérer le linge, les distributeurs sont très lents. Nous en avons besoin impérativement. | I23: Service médecine interne | J23: Appel
B24: 23 | D24: Structurant | G24: Accident sur l'autoroute empêche des paramédicaux d'arriver à l'heure | H24: Bonjour, je vous contacte, car j'ai plusieurs infirmiers et aides-soignants, qui m'ont contacté pour me dire qu'ils sont coincés sur l'autoroute. Apparement, il y a eu un accident grave, et ils ne savent pas exactement dans combien de temps, ils arriveront à l'hôpital.. ils m'ont assuré qu'ils nous tiendront au courant | I24: Cadre de santé | J24: Appel
B25: 24 | D25: Structurant | G25: Manque de personnel suite à accident et retards | H25: Bonjour, je vous recontacte car nos équipes aimeraient savoir quand ils pourront rentrer chez eux... Certains ont des problèmatiques de garde d'enfants et ne peuvent pas rester plus pour combler les retards, je ne sais pas quoi leur répondre. | I25: Cadre de santé | J25: Appel
B26: 25 | D26: Structurant | G26: Le logiciel des repas ne fonctionne plus | H26: Bonjour, je vous rappele pour remonter un dysfonctionnement. Les cuisines ne peuvent plus éditer les repas et aucun services ne peut distribuer les repas c'est très embêtant… | I26: Responsable technique du site | J26: Appel
B27: 26 | D27: Structurant | G27: ="Panne "&Applicatifs!$B$11&" (Transport des patients)" -> Panne Logiciel de transport des patients (Transport des patients) | H27: ="Bonjour, je n'arrive plus à commander un transport via "&Applicatifs!$B$11&". J'ai des patients qui doivent passer des scanners d'urgence ce matin, quelle est la procédure ? J'appelle directement le responsable des brancardiers ?" -> Bonjour, je n'arrive plus à commander un transport via Logiciel de transport des patients. J'ai des patients qui doivent passer des scanners d'urgence ce matin, quelle est la procédure ? J'appelle directement le responsable des brancardiers ? | I27: Service au choix | J27: Appel
B28: 27 | D28: Structurant | G28: Une mise à jour de sécurité s’est lancée sur les postes informatiques | H28: Bonjour, Une mise à jour s'est lancée sur les postes... Nous ne pourrons pas les utiliser pendant une dizaine de minutes. | I28: Accueil des urgences | J28: Appel
B29: 28 | D29: Structurant | G29: Hypothèse de piratage service gastro | H29: Bonjour, c'est le médecin coordinateur du service gastro, je pense que le poste a été piraté, il n'y a plus rien qui répond. Avez vous une procédure prévue pour ce type de cas, je ne sais absolument pas quoi faire et ni à qui m'adresser, je vous avoue être un peu perdu, j'aurais besoin d'aide. | I29: Service gastro | J29: Appel
B30: 29 | D30: Structurant | G30: ="Bug de "&Applicatifs!$B$12&" (Gestion des plannings)" -> Bug de Logiciel de gestion des plannings (Gestion des plannings) | H30: ="Bonjour, c'est X qui vous contacte, on m'a informé qu'en plus de "&Applicatifs!$B$5&" il y a un bug sur "&Applicatifs!$B$12&". On n'a plus aucune visibilité sur les plannings, il y a une page blanche qui s'affiche sans aucun contenu, est-ce que c'est normal ?" -> Bonjour, c'est X qui vous contacte, on m'a informé qu'en plus de Pastel il y a un bug sur Logiciel de gestion des plannings. On n'a plus aucune visibilité sur les plannings, il y a une page blanche qui s'affiche sans aucun contenu, est-ce que c'est normal ? | I30: Accueil des urgences | J30: Appel
B31: 30 | D31: Structurant | G31: Le DSI demande l'appui de l'ANSSI ou du CERT Santé | H31: Bonjour, nous observons des flux étranges et massifs, on ne sait pas encore d'où ça vient mais c'est très inquiétant. La bande passante a augmenté très fortement depuis cette nuit. Est-ce qu'on peut avoir l'appui de l'ANSSI ou du CERT Santé ? | I31: DSI Territoire - service infrastructure | J31: Appel
B32: 31 | D32: Structurant | G32: ="Bug de "&Applicatifs!$B$12&" (Gestion des plannings)" -> Bug de Logiciel de gestion des plannings (Gestion des plannings) | H32: ="Il y a des bugs sur "&Applicatifs!$B$12&", il semblerait que des créneaux soient apparus disponibles sans l'être. Par conséquent nous avons un grand nombre de rendez-vous qui se chevauchent et on ne peut même plus visualiser le planning de la journée sur certains postes." -> Il y a des bugs sur Logiciel de gestion des plannings, il semblerait que des créneaux soient apparus disponibles sans l'être. Par conséquent nous avons un grand nombre de rendez-vous qui se chevauchent et on ne peut même plus visualiser le planning de la journée sur certains postes. | I32: Accueil de l'hopital | J32: Appel
B33: 32 | D33: Structurant | G33: Clé USB en cause ? | H33: Nous avons une clé USB qu'on s'est transmise ce matin entre nous aux urgences, et depuis il y a beaucoup de problèmes je pense que c'est cette clé USB qui est source de problème | I33: Accueil des urgences | J33: Appel
B34: 33 | D34: Structurant | G34: Problème de garde d'enfants des employés | H34: Bonjour, je cherche à joindre Monsieur X, son enfant est à l'infirmerie et attend d'être récupé, il faudrait venir à l'école. | I34: Divers | J34: Appel
B35: 34 | D35: Structurant | G35: Panne ascenseur | H35: Bonjour nous avons une panne d'ascenseur, nous souhaitons rapidement régler le problème mais nous n'arrivons pas à identifier pour l'instant le problème et nous ne savons pas combien de temps cela prendra pour réparer.. | I35: Divers | J35: Appel
B36: 35 | D36: Structurant | G36: Fugue d'un patient | H36: Bonjour, un patient est introuvable depuis plus d'une heure. Cela nous préoccupe beaucoup, il est particulièrement instable. | I36: Service de psychiatrie | J36: Appel
B37: 36 | D37: Structurant | G37: Démarchage équipement médical | H37: Bonjour, C'est l'entreprise Distrimed qui vous contacte, nous sommes spécialisés dans la vente de matériel médical, nous aimerions vous infromer qu'en ce moment nous avons de superbes promotions sur les éléctrocardiographes avec des offres à partir de 589 euros. N'hesitez pas à directement consulter notre site internet également. | I37: Entreprise Distrimed | J37: Appel
B38: 37 | D38: Structurant | G38: Cadre inquiet à propos des informations qui fuitent sur les problèmes informatiques | H38: Bonjour X, je suis cadre aux urgences, je me permets de vous contacter directement car j'ai un patient ce matin aux urgences qui est journaliste TF1, et comme depuis ce matin il a pu entendre qu'on rencontre des problèmes informatiques, il arrête pas de me poser des question ainsi qu'aux autres urgentistes. Je crains qu'il transmette de fausses informations ou que cela soit divulgué | I38: Service des urgences | J38: Appel
B39: 38 | D39: Structurant | G39: Responsable d’un service en congé | H39: Bonjour, nous avons une opération très importante de programmée aujourd'hui, elle ne peut pas être déprogrammée au service X mais le responsable de ce service est en congé, Nous attendons vos consignes | I39: Service de chirurgie pédiatrique | J39: Appel
B40: 39 | D40: Structurant | G40: Personne influente arrivée aux urgences - que faire ? | H40: C'est les urgences, nous avons X qui vient d'être admis aux urgences, il a fait un AVC, faut à tout prix faire quelque chose, les rumeurs ciruclent vite, nous avons pleins de patients qui viennent nous poser la question, la ligne téléphonique est débordée, c'est l'affolement total. qu'est ce qu'on doit faire ? pourrions nous avoir du renfort quelque chose avant que cela ne devienne incontroable ? | I40: Service des urgences | J40: Appel
B41: 40 | D41: Structurant | G41: Identification de fichiers chiffrés | H41: Bonjour, je viens d'analyser les serveurs des applications en panne, il y a de nombreux fichiers avec l'extension .xyz, et ils sont illisibles. Savez-vous ce qu'il se passe ? | I41: Equipe DSI | J41: Appel
B42: 41 | D42: Structurant | G42: ="Panne "&Applicatifs!$B$7&" (PACS)" -> Panne PACS (PACS) | H42: ="Bonjour, "&Applicatifs!$B$7&" est inaccessible, on est obligé de se déplacer pour accéder aux résultats d'imagerie. On perd un temps fou !" -> Bonjour, PACS est inaccessible, on est obligé de se déplacer pour accéder aux résultats d'imagerie. On perd un temps fou ! | I42: Service au choix | J42: Appel
B43: 42 | D43: Structurant | G43: Appel vers le DSI : Alertes sur les consoles de supervision | H43: ="Bonjour, nous avons des alertes qui remontent, les dysfonctionnement s'affichent en rouge. Le réseau est saturé depuis cette nuit, on ne comprend pas l'origine des flux. Plusieurs applications sont en panne : "&Applicatifs!$B$7&", "&Applicatifs!$B$5&", "&Applicatifs!$B$6&", "&Applicatifs!$B$9&", "&Applicatifs!$B$12&". C'est très inquiétant. On vérifie les bases de données, on redémarre les serveurs et, si ça ne suffit pas, on alertera l'hébergeur." -> Bonjour, nous avons des alertes qui remontent, les dysfonctionnement s'affichent en rouge. Le réseau est saturé depuis cette nuit, on ne comprend pas l'origine des flux. Plusieurs applications sont en panne : PACS, Pastel, INLOG, Logiciel de gestion des repas, Logiciel de gestion des plannings. C'est très inquiétant. On vérifie les bases de données, on redémarre les serveurs et, si ça ne suffit pas, on alertera l'hébergeur. | I43: Equipe DSI | J43: Appel
B44: 43 | D44: Structurant | G44: Appel vers la qualité : Préparation des services au mode dégradé | H44: ="Bonjour, on observe de nombreuses coupures applicatives. Il faut passer en mode dégradé dans les services. Ce qui est en panne : "&Applicatifs!$B$7&", "&Applicatifs!$B$5&", "&Applicatifs!$B$6&", "&Applicatifs!$B$9&", "&Applicatifs!$B$12&"." -> Bonjour, on observe de nombreuses coupures applicatives. Il faut passer en mode dégradé dans les services. Ce qui est en panne : PACS, Pastel, INLOG, Logiciel de gestion des repas, Logiciel de gestion des plannings. | I44: Equipe DSI | J44: Appel
B45: 44 | D45: Structurant | G45: Personne médiatique arrivée aux urgences - quoi faire ? | H45: C'est les urgences, nous avons reçu un influenceur connu qui a fait un accident de moto et nous avons plein de patients qui viennent nous poser la question sur lui, des jeunes s'amusent à appeler sur notre ligne téléphonique et il y a même la presse people qui est sur place. Qu'est ce qu'on doit faire ? | I45: Service des urgences | J45: Appel
B46: 45 | D46: Structurant | G46: Arrivée de l'Unité Médico Juiciaire et agression du médecin N°1 | H46: Bonjour, un médecin vient d'être agressé un médecin au niveau de l'Unité Médico Judiciaire, il est dans un état grave. | I46: Service des urgences | J46: Appel
B47: 46 | D47: Structurant | G47: Altercation entre médecins et policiers N°2 | H47: Bonjour suite à l'agression de notre médecin, les tensions sont montées entre les agents de police qui ne sont pas parvenus à régler assez rapidement la situation et les médecins. Donc le service médico judiciaire ne souhaite plus travailler pour l'instant. Nous essayons d'arranger les choses mais tout le monde est sur les nerfs, c'est compliqué de gérer actuellement | I47: Service des urgences | J47: Appel
B48: 47 | D48: Structurant | G48: Analyse du service infrastructure | H48: Bonjour, nous avons identifié des surchauffes au niveau de vos serveurs. Nous sommes en train de regarder de quoi il s'agit, à priori des scans réseau et des périphériques malveillants… | I48: DSI Territoire - service infrastructure | J48: Appel
B49: 48 | D49: Structurant | G49: Analyse du service infrastructure | H49: Bonjour c'est le service Infra de la DSI Territoire, on vient avec des précisions sur la nature de la menace : - Multiples scans réseaux très intensifs - Tentatives de brut-force massives - Trafic réseau sortant plus important que d'habitude - Branchement de périphérique "Bad USB" | I49: DSI Territoire - service infrastructure | J49: Appel
B50: 49 | D50: Structurant | G50: Analyse du service infrastructure | H50: Bonjour c'est le service Infra de la DSI Territoire qui vous rappelle, ça pourrait être une cyberattaque. Nous continuons nos investigations pour pouvoir préparer un début de réponse. En attendant, il faut débrancher tous les systèmes, couper le réseau externe et remasteriser les postes, voire les remplacer. | I50: DSI Territoire - service infrastructure | J50: Appel
B51: 50 | D51: Structurant | G51: ="Coupure du DPI : "&Applicatifs!$B$4&" ne fonctionne plus" -> Coupure du DPI : CrossWay ne fonctionne plus | H51: =Applicatifs!$B$4&" est en panne, on n'a plus du tout accès au DPI ! Avec toutes ces coupures ce n'est plus possible de travailler !!!" -> CrossWay est en panne, on n'a plus du tout accès au DPI ! Avec toutes ces coupures ce n'est plus possible de travailler !!! | I51: Service au choix | J51: Appel
B52: 51 | D52: Structurant | G52: Les postes informatiques des admissions ne répondent plus | H52: Bonjour, je vous contacte en urgence car tous les postes informatiques au niveau du guichet des admissions aux urgences sont maintenant entièrement éteints avec des écrans noirs. Nous continuons de traiter les demandes en manuscrit mais ça ne va pas être possible indéfiniment, ça prend beaucoup de temps et nous sommes de plus en plus saturés. | I52: Accueil des urgences | J52: Appel
B53: 52 | D53: Structurant | G53: QUID de la robotisation milieu hospitalier | H53: Bonjour je suis journaliste pour France 2, que pensez vous de la question qui fait polémique sur les réseaux : celle de la robotisation en milieu hospitalier ? Qu'en pensez vous ? Est ce que c'est un veritable problème pour les hopitaux ? | I53: Journalistes | J53: Appel
B54: 53 | D54: Structurant | G54: Les imprimantes du centre hospitalier impriment le message de rançon | H54: Improviser | I54: Service au choix | J54: Appel
B55: 54 | D55: Structurant | G55: Envoi des logs au CERT Santé et à l'ANSSI | H55: Bonjour, on a du mal à identifier les problèmes et l'origine des coupures. On va contacter le CERT Santé et l'ANSSI pour leur envoyer des logs. | I55: Equipe DSI | J55: Appel
B56: 55 | D56: Structurant | G56: Point de situation | H56: « Bonjour, Nous vous contactons suite aux messages que nous avons vu apparaitre sur les réseaux sociaux concernant un potentiel incident de sécurité touchant vos systèmes. Pouvez-vous nous en dire plus sur les événements ? En vous remerciant par avance » | I56: ANSSI | J56: Appel
B57: 56 | D57: Structurant | G57: Fausses images circulant de scènes de panique | H57: Bonjour je suis journaliste du Parisien, nous avons reçu des images et photos qui témoignent d'une prise de panique au sein de l'hôpital ? Que pouvez vous nous dire à ce sujet? | I57: Journalistes | J57: Appel
B58: 57 | D58: Structurant | G58: Théorie de la panne liée à la vetusté | H58: Bonjour, je suis une journaliste du journal le Monde, je voudrais savoir afin de rédiger mon article si les différentes pannes auxquelles vous faites face sont liée à la vétusté du matériel des hopitaux ? | I58: Journalistes | J58: Appel
B59: 58 | D59: Structurant | G59: Théorie de la panne liée à manque de moyen | H59: Bonjour, je suis journaliste pour 20 minutes je voudrais savoir dans le cadre de toute cette politique qui tourne autour de l'hôpital si les pannes auxuqelles vous faites face sont le résultat d'un manque de moyens des hôpitaux ? La robotisation est bien mise en place mais l'entretient du matériel de l'hopital ne suit pas ? | I59: Journalistes | J59: Appel
B60: 59 | D60: Structurant | G60: ="Dysfonctionnement "&Applicatifs!$B$8&" (Armoires informatisées)" -> Dysfonctionnement Armoires informatisées (Armoires informatisées) | H60: Improviser | I60: Service au choix | J60: Appel
B61: 60 | D61: Structurant | G61: ="Problème "&Applicatifs!$B$13&" (Gestion des stocks)" -> Problème Pharma® (Gestion des stocks) | H61: ="Bonjour, on vous contacte car depuis ce matin "&Applicatifs!$B$13&" ne fonctionne plus. On essaye de pallier à la situation en allant chercher nous-mêmes les commandes mais là on accumule beaucoup de retard et les services se plaignent. Savez-vous ce qu'il en est ?" -> Bonjour, on vous contacte car depuis ce matin Pharma® ne fonctionne plus. On essaye de pallier à la situation en allant chercher nous-mêmes les commandes mais là on accumule beaucoup de retard et les services se plaignent. Savez-vous ce qu'il en est ? | I61: Pharmacie | J61: Appel
B62: 61 | D62: Structurant | G62: Attaque au rançongiciel Ruyk | H62: Mail : Your network has been penetrated. All files on each host in the network have been encrypted with a strong algorithm. Backups were either encrypted Shadow copies also removed, so F8 or any other methods may damage encrypted data but not recover. We exclusively have decryption software for your situation. More than a year ago, world experts recognized the impossibility of deciphering by any means except the original decoder. No decryption software is available in the public. Antiviruse companies, researchers, IT specialists, and no other persons cant help you encrypt the data. DO NOT RESET OR SHUTDOWN - files may be damaged. DO NOT DELETE readme files. To confirm our honest intentions.Send 2 different random files and you will get it decrypted. It can be from different computers on your network to be sure that one key decrypts everything. 2 files we unlock for free To get info (decrypt your files) contact us at GHTNOVOMacGlen@protonmail.com or GHTNOVOMacGlen@tutanota.com You will receive btc address for payment in the reply letter Ryuk No system is safe | I62: Attaquants | J62: Appel
B63: 62 | D63: Structurant | G63: Il y a des fichiers cryptés : attaques rançonlogiciel Ruyk | H63: تم اختراق شبكتك. تم تشفير جميع الملفات الموجودة على كل مضيف في الشبكة بخوارزمية قوية. تم تشفير النسخ الاحتياطية تمت إزالة نسخ الظل أيضًا ، لذلك قد يؤدي استخدام F8 أو أي طرق أخرى إلى إتلاف البيانات المشفرة ولكن لا يتم استردادها. لدينا حصريًا برنامج فك تشفير لحالتك. منذ أكثر من عام ، أدرك خبراء العالم استحالة فك التشفير بأي وسيلة باستثناء وحدة فك التشفير الأصلية. لا يوجد برنامج فك تشفير متاح للجمهور. لا تستطيع شركات مكافحة الفيروسات والباحثون والمتخصصون في تكنولوجيا المعلومات وأي أشخاص آخرين مساعدتك في تشفير البيانات. لا تقم بإعادة الضبط أو الإغلاق - فقد تتلف الملفات. لا تحذف الملفات التمهيدية. لتأكيد نوايانا الصادقة أرسل ملفين عشوائيين مختلفين وسيتم فك تشفيرهما. يمكن أن يكون من أجهزة كمبيوتر مختلفة على شبكتك للتأكد من قيام مفتاح واحد بفك تشفير كل شيء. 2 ملف نفتحه مجانًا للحصول على معلومات (فك تشفير ملفاتك) اتصل بنا على GHTNOVOMacGlen@protonmail.com أو GHTNOVOMacGlen@tutanota.com سوف تتلقى عنوان btc للدفع في خطاب الرد ريوك لا يوجد نظام آمن | I63: Attaquants | J63: Appel
B64: 63 | D64: Structurant | G64: Il y a des fichiers cryptés : attaques rançonlogiciel Ruyk | H64: В вашу сеть проникли. Все файлы на каждом узле сети были зашифрованы сильным алгоритмом. Резервные копии были либо зашифрованы. Теневые копии также удалены, поэтому F8 или любые другие методы могут повредить зашифрованные данные, но не восстановить их. Для вашей ситуации у нас есть исключительно программное обеспечение для расшифровки. Более года назад мировые эксперты признали невозможность расшифровки любыми средствами, кроме оригинального дешифратора. В открытом доступе нет ни одного программного обеспечения для расшифровки. Антивирусные компании, исследователи, IT-специалисты и никакие другие лица не могут помочь вам зашифровать данные. НЕ ПЕРЕЗАПУСКАЙТЕ И НЕ ВЫКЛЮЧАЙТЕ - файлы могут быть повреждены. НЕ УДАЛЯЙТЕ файлы readme. Чтобы подтвердить наши честные намерения, отправьте 2 разных случайных файла и получите их расшифровку. Это может быть с разных компьютеров в вашей сети, чтобы быть уверенным, что один ключ расшифрует все. 2 файла, которые мы разблокируем бесплатно Для получения информации (расшифровки ваших файлов) свяжитесь с нами по адресу GHTNOVOMacGlen@protonmail.com или GHTNOVOMacGlen@tutanota.com Вы получите btc адрес для оплаты в ответном письме. Рюк Ни одна система не является безопасной Переведено с помощью www.DeepL.com/Translator (бесплатная версия) | I64: Attaquants | J64: Appel
B65: 65 | D65: Structurant | G65: ="Problème "&Applicatifs!$B$13&" (Gestion des stocks)" -> Problème Pharma® (Gestion des stocks) | H65: ="Bonjour, on vous contacte car depuis ce matin "&Applicatifs!$B$13&" ne fonctionne plus. C'est la panique à la pharmacie et tout est très long. Savez-vous ce qu'il en est ?" -> Bonjour, on vous contacte car depuis ce matin Pharma® ne fonctionne plus. C'est la panique à la pharmacie et tout est très long. Savez-vous ce qu'il en est ? | I65: Service au choix | J65: Appel
B66: 66 | D66: Structurant | G66: Appel énervé de l'ARS de ne pas avoir l'info dans les temps et de ne pas être impliquée | H66: SI PAS PREVENUE À CE STADE Bonjour, je viens d'apprendre, indirectement, que vos sites sont victimes d'une cyberattaque. Par les réseaux sociaux... N'auriez-vous pas oublié de me prévenir ? J'aimerais que ce soit la dernière fois que je vous appelle pour avoir des informations. C'est à vous de me tenir informé-e ! | I66: ARS | J66: Appel
B67: 67 | D67: Structurant | G67: Une fois le signalement réalisé A adapter au besoin Stimuli 2 | H67: Stimuli 2 Une fois le signalement réalisé (après stimuli 1 ou après signalement). N’hésitez pas à modifier /supprimer les questions en fonction des détails. Cette liste de question peut être très utile si vous voulez inciter les cellules de crise à faire un point de situation. « Bonjour, Nous avons bien pris en compte votre signalement, enregistré sous la référence [RM#XXXXXX]. Dans le cadre de notre procédure de traitement d’incident, nous souhaiterions obtenir davantage d’informations. Vous trouverez ci-après les éléments demandés ainsi que des premières recommandations. • Nom et Prénom / Courriel / Numéro de téléphone du RSSI et/ou de la personne en charge de cet incident • Quelles sont les machines concernées par l’infection ? Quels types de fichiers ont été chiffrés ? Le SI compromis est-il en lien avec d’autres SI ? • Quel est l’impact de cet incident sur la poursuite de vos activités ? • Date et heure de l’infection ___________________________ (possible de le faire en deux appels)_____________________________ • Connaissez-vous le vecteur de la compromission (courriel malveillant, exploitation de vulnérabilité, compromission de SI, etc.) ? • Connaissez-vous le rançongiciel ? Sa version ? • Quelle est l’extension des fichiers chiffrés ? • Avez-vous des empreintes numériques (MD5, SHA1, SHA256 ...), une souche du rançongiciel ou des captures d’écran à nous transmettre ? • Pouvez-vous communiquer la demande de rançon, les adresses courriel impliquées, les portefeuilles de Bitcoin ? • Avez-vous des sauvegardes saines qui permettraient de restaurer le ou les systèmes infectés ? • Avez-vous engagé un prestataire pour vous aider à remédier à cette attaque ? Si oui, lequel ? • Quelles ont été les mesures réactives prises à la suite de cet incident ? • Dans le cas où des données à caractère personnel aient été impactées, avez-vous déclaré l’incident à la CNIL ? • Envisagez-vous ou avez-vous déjà effectué un dépôt de plainte ? • Il est très peu probable que les données puissent être déchiffrées. Toutefois, sollicitez-vous une assistance de l’ANSSI dans vos actions de remédiation ? Si oui, pour quel(s) champs d’intervention ? Notez qu’à ce stade, le niveau d’engagement de l’ANSSI ne peut être défini. Dans l’optique d’une démarche pénale (recommandée), nous vous rappelons que vous êtes invité à conserver sans y apporter de modification, tout document ou information établissant les faits et qui constitueraient potentiellement des éléments de preuve : - copies physiques des disques durs (ou VM) des postes compromis ; - copies des journaux d’événements disponibles sur tout équipement réseau qui auraient pu permettre la transmission des codes malveillants. Enfin, selon le type et la version du rançongiciel, il est possible qu’il existe un outil ou des clés de déchiffrement dédiés. Un référentiel de ces solutions est disponible sur le site Internet No More Ransom (https://www.nomoreransom.org/fr/index.html). Nous vous invitons à consulter les conseils préalables et guides d’utilisation avant toute opération de déchiffrement. Également, si vous le souhaitez une personne en charge de la communication à l’ANSSI va prendre contact avec vos communicants. Pouvez-vous me transmettre leurs coordonnées ? Je vous propose de planifier rapidement un point d’étape. » => à faire uniquement si vous souhaitez jouer ce volet là accompagnement à la communication de crise. | I67: ANSSI | J67: Appel
B68: 68 | D68: Structurant | G68: DT ARS qui demande un point de situation | H68: Bonjour, c'est la "DT ARS", je vous appelle pour faire un point rapide sur la situation : - quelles sont vos certitudes pour l'instant ? - quels sont les premiers impacts ? - à quoi doit-on se préparer ? | I68: ARS | J68: Appel
B69: 69 | D69: Structurant | G69: Sollicitation du ministère (CORRUS) | H69: Bonjour, c'est Caroline Le Borgne Pouvez vous nous faire un point sur la situation ? | I69: CORRUS | J69: Appel
B70: 71 | D70: Structurant | G70: Appel de l’ARS Questions sur la vaccination | H70: Bonjour, Pouvez vous nous faire un point sur la situation ? QUID de la vaccination ? Y a t-il un risque pour l'unité ? | I70: ARS | J70: Appel
B71: 72 | D71: Structurant | G71: Pb dossier partagé | H71: Bonjour, Nous pensons que notre dossier partagé au service gastro a été corrompu. Que fait-on ? | I71: Service gastro Médecin coordinateur | J71: Appel
B72: 73 | D72: Structurant | G72: Communication ARS | H72: L'ARS demande des éléments de langage pour communication. | I72: ARS | J72: Appel
B73: 74 | D73: Structurant | G73: Message de menace en français | H73: Le temps presse... si vous ne payez pas rapidement nous allons diffuser des données personnelles en amuse bouche ET PAS N'IMPORTE LESQUELS on vous le garantit ! Bougez vous | I73: Attaquants | J73: Appel
B74: 75 | D74: Structurant | G74: Message de menace en russe | H74: ВРЕМЯ ИДЁТ, ВРЕМЯ СПЕШИТ, ЕСЛИ НЕ ЗАПЛАТИТЕ ТО УВИДИТЕ ЧТО С ВАМИ БУДЕТ ! | I74: Attaquants | J74: Appel
B75: 76 | D75: Structurant | G75: Message en Arabe de menace | H75: الوقت يمضي ، إذا لم تدفع ، فراجع ما سيحدث لك! | I75: Attaquants | J75: Appel
B76: 77 | D76: Structurant | G76: Message en Espagnol de menace | H76: EL TIEMPO PASA, SI NO PAGAS ENTONCES VERAS LO QUE PASA! | I76: Attaquants | J76: Appel
B77: 78 | D77: Structurant | G77: Message en Moore de menace | H77: Te waa panui ... ki te kore koe e utu tere ka tohaina e maatau o raatau ake tuhinga ma te ngahau, kaua e uru ki nga mea e taurangi ana matou! Haere tonu | I77: Attaquants | J77: Appel
B78: 79 | D78: Structurant | G78: ="Perte du monitorage "&Applicatifs!$B$14&" (USC, USIC, USINV)" -> Perte du monitorage Logiciel de surveillance des patients (Général) (USC, USIC, USINV) | H78: Bonjour, on a perdu le monitorage des patients. On est obligé de se déplacer dans chaque chambre pour surveiller l'état des patients. On a besoin de renfort, on ne peut pas se dédoubler ! | I78: USC ou USIC ou USINV | J78: Appel
B79: 80 | D79: Structurant | G79: Plus possible de créer des dossiers d'admission au niveau des urgences | H79: Bonjour, on est complétement débordés qu'est ce qu'on fait ?? | I79: Accueil des urgences | J79: Appel
B80: 81 | D80: Structurant | G80: Appel énervé d’un médecin qui n’arrive plus à accéder aux dossiers de ses patients | H80: Bon ça commence à bien faire, c'est Jean Luc médecin en USIC, je n'arrive pas à accéder aux dossiers de mes patients, vous trouvez ça normal en toute honnêteté ? Je n'ai pas de temps à perdre, comment je fais si un des patients me fait une crise cardiaque là tout de suite, j'ai aucune information rien rien absolument rien. Je rentre chez moi dans ce cas là et puis vous m'appelez quand c'est reglé ! | I80: USIC | J80: Appel
B81: 82 | D81: Structurant | G81: Saturation progressive aux urgences après appel à la régulation | H81: Bonjour, le flux d'arrivées aux urgences devient trop important, nous serons bientôt saturés. Nous avons appelé la régulation... Pas de place au delà de 4-5 véhicules, donc coincés dans leurs véhicules | I81: Accueil des urgences | J81: Appel
B82: 83 | D82: Structurant | G82: CTA appelle, envoi officier | H82: AR (ambu réa) se plaint Un officier se présente aux urgences parce qu'il y a beaucouup de VSAV qui attendent "Bonjour, vous pouvez m'expliquer ce qui se passe ? Pourquoi il y a un engorgement de VSAV ?" | I82: CTA | J82: Appel
B83: 84 | D83: Structurant | G83: Si besoin d'un accompagnement Communication par l’ANSSI | H83: « Bonjour, Je travaille au sein de la division de la communication de l’ANSSI et je prends contact avec vous suite aux échanges que vous avez avec l’agence sur votre incident. On se propose de vous accompagner pour anticiper et/ou préparer vos éléments de communication externe et interne en cas de visibilité de l’attaque. Des premiers éléments de communication interne ou externe ont-ils déjà été transmis ? Avez-vous été sollicité par les médias ? Pour construire votre stratégie de communication, plusieurs actions à mener dans un premier temps : définition des parties prenantes (interne, clients, autorités, etc.), des cibles et objectifs de votre communication ainsi que des éventuels points de vigilance spécifiques à votre entité (notoriété/image de marque, exposition médiatique), votre secteur d’activité (actualités du marché, etc.), votre calendrier (obligation de communication financière, rachat, etc.), etc. Nous pouvons vous accompagner dans la rédaction de vos éléments de communication (communiqué de presse, communication interne). Si vous souhaitez mentionner l’ANSSI, nous demanderons à valider la mention. » | I83: ANSSI | J83: Appel
B84: 85 | D84: Structurant | G84: Si réponse à la demande d’information par l’Agence (stimuli 2) | H84: « Bonjour, Voici quelques éléments issus de notre analyse. Nous avons pu identifier le code malveillant à l’origine de l’attaque, il s’agirait du rançongiciel RYUK, Nous n’avons cependant pas encore identifié le vecteur d’infection initiale. Ce code malveillant chiffre les fichiers présents sur la machine ainsi que sur les partages réseau accessibles. Il supprime également les copies cachées. Votre SI ne retrouvera pas un fonctionnement normal pendant une semaine au moins. Il faudra prévoir de travailler quasiment sans informatique et donc en mode dégradé durant cette période. Nous vous invitons à consulter les informations suivante sur le ranconlogiciel concerné : https://www.cert.ssi.gouv.fr/uploads/CERTFR-2019-CTI-001.pdf » | I84: ANSSI | J84: Appel
B85: 86 | D85: Structurant | G85: ="Bug de "&Applicatifs!$B$15&" (Gestion de la température)" -> Bug de Logiciel de gestion de la température (Laboratoire) (Gestion de la température) | H85: ="Bonjour, on est très inquiet au laboratoire, on vient de voir que "&Applicatifs!$B$15&" ne fonctionnait pas cette nuit. On a aucun moyen de savoir si les frigos ont été maintenus à la bonne température. Ça pose un gros problème pour les poches sanguines, on ne sait pas quoi faire là." -> Bonjour, on est très inquiet au laboratoire, on vient de voir que Logiciel de gestion de la température (Laboratoire) ne fonctionnait pas cette nuit. On a aucun moyen de savoir si les frigos ont été maintenus à la bonne température. Ça pose un gros problème pour les poches sanguines, on ne sait pas quoi faire là. | I85: Laboratoire | J85: Appel
B86: 87 | D86: Structurant | G86: Débranchement des câbles réseaux | H86: Bonjour c'est l'ANSSI à l'appareil, il faut débrancher les câbles réseaux en attendant que nos équipes interviennent | I86: ANSSI | J86: Appel
B87: 88 | D87: Structurant | G87: Ne pas prendre contact avec attaquants | H87: Bonjour c'est encore l'ANSSI comme nous le préconisons toujours il ne faut surtout pas prendre contact avec l'attaquant ! Pour l'instant ce que l'on vous préconise c'est surtout de ne pas éteindre les machines infectés, en attendant qu'on réussise à rassembler plus d'éléments et d'informations. | I87: ANSSI | J87: Appel
B88: 89 | D88: Structurant | G88: Une secrétaire a envoyé un mail à l'attaquant en demandant le prix de la rançon | H88: Bonjour, je vous appelle car ma collègue aux urgences a envoyé un mail aux attaquants sur le mail indiqué pour demander le montant de la rançon.... | I88: Accueil des urgences | J88: Appel
B89: 90 | D89: Structurant | G89: Screen des attaquants d'une image avec la demande de rançon | H89: Screen des attaquants d'une image avec la demande de rançon | I89: Attaquants | J89: Appel
B90: 91 | D90: Structurant | G90: Analyse du CERT Santé | H90: Bonjour c'est le CERT Santé, on a analysé quelques logs, et on a identifié une compromission de l'AD et du server Exchange. Un compte admin a été créé cette nuit, et des exfiltration de données ont eu lieu. On peut considérer que toutes les données ont été volées... | I90: CERT Santé | J90: Appel
B91: 92 | D91: Structurant | G91: Prise de contact du SIB | H91: Bonjour, c'est le SIB. Nous avons été contacté par vos équipes suite aux dysfonctionnements que vous rencontrez depuis ce matin. Pour nous il s'agit d'une cyberattaque, on observe des exfiltrations de données vers des serveurs extérieurs. Il vaut mieux couper les accès tout de suite et isoler votre réseau. | I91: SIB (hébergeur de données de santé) | J91: Appel
B92: 93 | D92: Structurant | G92: Nettoyage du matériel d'endoscopie | H92: Bonjour, comme si ça ne suffisait pas on a aussi un problème avec le laveur du matériel. On ne peut plus assurer le nettoyage du matériel d'endoscopie. | I92: Pharmacie | J92: Appel
B93: 94 | D93: Structurant | G93: Saturation d’appels pour dire qu’il y a un problème sur les ordinateurs | H93: Il y a des problèmes sur les postes ! Que fait-on ? | I93: Service au choix | J93: Appel
B94: 95 | D94: Structurant | G94: Message de menace en français | H94: Bonjour. Je suis un hacker,et j’ai accès à l'ensemble de vos systèmes informatiques et à vos systèmes d'exploitation Cela fait plusieurs mois que je surveille votre hôpital. Si vous ne comprenez pas, ce qui arrive je vais vous l’expliquer. Un virus de type cheval de Troie me donne un accès complet et un contrôle intégral d’un ordinateur ou d’un autre appareil. Cela signifie que je suis capable de surveiller votre écran, le manipuler sans que vous ne puissiez le savoir. JE SUIS D'HUMEUR TAQUINE, JE VAIS PEUT-ÊTRE DANS PEU DE TEMPS COUPER VOS APPAREILS MÉDICAUX POUR M'AMUSER UN PEU... TIC TAC, TIC TAC, TIC TAC | I94: Attaquants | J94: Appel
B95: 96 | D95: Structurant | G95: ="Dysfonctionnement "&Applicatifs!$B$16&" (Suivi des chimiothérapies)" -> Dysfonctionnement Chimio (Suivi des chimiothérapies) | H95: ="Le logiciel "&Applicatifs!$B$16&" ne fonctionne plus ! Que faire ? On est bloqué au service oncologie, on ne peut plus réaliser les chimiothérapies planifiées aujourd'hui car il est impossible de se connecter." -> Le logiciel Chimio ne fonctionne plus ! Que faire ? On est bloqué au service oncologie, on ne peut plus réaliser les chimiothérapies planifiées aujourd'hui car il est impossible de se connecter. | I95: Service d'oncologie | J95: Appel
B96: 97 | D96: Structurant | G96: Le Maire assure son soutien | H96: Je vous apporte tout mon soutien et je m'engage à réunir tous les moyens pour vous venir en aide. N'hesitez pas à contacter mon cabinet. | I96: Mairie | J96: Appel
B97: 98 | D97: Structurant | G97: Point de situation | H97: Bonjour, Pourriez-vous nous faire un point sur la situation ? | I97: Mairie | J97: Appel
B98: 99 | D98: Structurant | G98: Mobilisation citoyenne pour aider | H98: Bonjour, la Mairie a mobilisé des citoyens qui sont disponibles pour aider l'hôpital à gérer la crise en cours.. nous vous en informons et en cas de besoin n'hesitez pas. | I98: Mairie | J98: Appel
B99: 100 | D99: Structurant | G99: ="Panne "&Applicatifs!$B$7&" (PACS)" -> Panne PACS (PACS) | H99: Bonjour, il y a des problèmes de transmission au niveau de l'imagerie. C'est très gênant, il faut faire des allers-retours pour accéder à l'imagerie mais dans notre service chaque minute compte ! Comment régler la situation ? | I99: Service des urgences | J99: Appel
B100: 101 | D100: Structurant | G100: ="Dysfonctionnement "&Applicatifs!$B$17&" (Gestion des salles de bloc)" -> Dysfonctionnement HM Bloc (Hopital Manager) (Gestion des salles de bloc) | H100: ="Bonjour, le service des urgences nous a contacté, apparemment le logiciel "&Applicatifs!$B$17&" qui permet de gérer les salles de bloc ne fonctionne plus (expliquer pourquoi cela pose problème)." -> Bonjour, le service des urgences nous a contacté, apparemment le logiciel HM Bloc (Hopital Manager) qui permet de gérer les salles de bloc ne fonctionne plus (expliquer pourquoi cela pose problème). | I100: Equipe Technique | J100: Appel
B101: 102 | D101: Structurant | G101: Témoignage du fiasco du SEGUR de la santé | H101: Ce texte est dans la continuité des lois réorganisant les établissements de santé au profit d'une vision budgétaire et managériale, au détriment de la qualité des soins et des conditions de travail des personnels. Ce n'est qu'une tentative, incomplète, d'assemblage de mesures mal articulées entre elles. | I101: Médecin | J101: Appel
...

Sheet Applicatifs
F1: Listes
F2: Modalité | G2: Type d'inject | H2: Destinataire | I2: Personnages
A3: Type d'applicatif | B3: Nom du logiciel | C3: Présence | D3: Commentaire | F3: Appel | G3: Structurant | H3: CCD CHU | I3: Technicien informatique
A4: DPI (Général) | B4: CrossWay | C4: Oui | F4: SMS | G4: Saturant | H4: CCOPS CHU | I4: Infirmière
A5: GAM (Urgences) | B5: Pastel | C5: Oui | F5: E-mail | H5: ARS | I5: Médecin
A6: SGL (Système de Gestion du Laboratoire) | B6: INLOG | C6: Oui | F6: A l'oral par le coach | H6: Préfecture | I6: Cadre de santé
A7: PACS (Imagerie) | B7: PACS | C7: Oui | H7: CCD CHOR | I7: Secrétaire médicale
A8: Armoires informatisées | B8: Armoires informatisées | C8: Oui | H8: CCOPS CHOR | I8: Chef de service des urgences
A9: Logiciel de gestion des repas | B9: Logiciel de gestion des repas | C9: Oui | H9: CCD GHER | I9: Responsable laboratoire
A10: Logiciel de prescription | B10: Logipren | C10: Oui | H10: CCOPS GHER | I10: Responsable imagerie
A11: Logiciel de transport des patients | B11: Logiciel de transport des patients | C11: Oui | H11: CC Biomédicale CHU Sud | I11: Chef de service réanimation
A12: Logiciel de gestion des plannings | B12: Logiciel de gestion des plannings | C12: Oui | I12: Chef de service cardiologie
A13: Logiciel de gestion des stocks (Pharmacie) | B13: Pharma® | C13: Oui | I13: Responsable pharmacie
A14: Logiciel de surveillance des patients (Général) | B14: Logiciel de surveillance des patients (Général) | C14: Oui | I14: Responsable maternité
A15: Logiciel de gestion de la température (Laboratoire) | B15: Logiciel de gestion de la température (Laboratoire) | C15: Oui | I15: Chirurgien
A16: Logiciel de suivi des chimiothérapies (Oncologie) | B16: Chimio | C16: Oui | I16: Psychiatrie
A17: Logiciel de gestion des salles de bloc (Urgences) | B17: HM Bloc (Hopital Manager) | C17: Oui | I17: Accueil
I18: Stérilisation
A19: Autres (Santé) | B19: Présence | C19: Commentaire | I19: Oncologie
A20: Pneumatique ? | B20: Oui | I20: Responsable RH
A21: Distributeur de linge ? | B21: Oui | I21: Responsable service batimentaire
I22: Membre d'un syndicat
A23: Autres (SI) | B23: Commentaire | C23: Corps | I23: Chargée de communication du CHU
A24: Réseau bâtimentaire ? | C24: Bonjour, les badges ne fonctionnent plus, on ne peut plus ouvrir les portes des bâtiments, les équipes ne peuvent plus entrer dans les batîments. Il y a aussi des portes qui ne se verrouillent plus et des patients qui circulent librement. Il faut trouver une solution rapidement ! | G24: ❌ | H24: ✅ | I24: Service juridique
A25: Réseau téléphonique IP ? | C25: Bonjour, sans téléphonie IP nous sommes sollicités car personne ne sait comment se joindre. C'est la panique partout là ! | I25: ANSSI
I26: CERT Santé
I27: ADVENS (PRIS)
I28: Officier CODIS 974
I29: Médecin syndicaliste du CHU Docteur Genou
I30: Permanence du cabinet du ministre de l'intérieur
I31: CORRUSS
I32: SAMU
I33: Cabinet du Premier ministre
I34: ZINFOS 974
I35: Centre pénitentier de Saint-Denis - Directeur de la prison
I36: Journaliste
I37: EFS
... I53: Prestataire biomédical - BioCom

Sheet Liste
A1: Liste
A2: Oui
A3: Non
